Metadata-Version: 2.1
Name: whichimg
Version: 1.0.3
Summary: blazing fast template matching when possible images are all known. Good for GUI scripting.
Home-page: https://github.com/Madoshakalaka/whichimg
Author: Matt Yan
Author-email: syan4@ualberta.ca
License: UNKNOWN
Project-URL: Bug Reports, https://github.com/Madoshakalaka/whichimg/issues
Project-URL: Funding, https://github.com/Madoshakalaka/whichimg
Project-URL: Say Thanks!, https://github.com/Madoshakalaka/whichimg
Project-URL: Source, https://github.com/Madoshakalaka/whichimg
Platform: UNKNOWN
Classifier: Development Status :: 5 - Production/Stable
Classifier: Intended Audience :: Developers
Classifier: Topic :: Software Development :: Build Tools
Classifier: License :: OSI Approved :: MIT License
Classifier: Programming Language :: Python :: 3.6
Classifier: Programming Language :: Python :: 3.7
Requires-Python: >=3.6
